jupyter_sdk/__init__.py
jupyter_sdk/_version.py
jupyter_sdk/handlers.py
jupyter_sdk/tests/__init__.py
jupyter_sdk/tests/test_handlers.py
jupyter_sdk-0.0.2.data/data/etc/jupyter/jupyter_notebook_config.d/jupyter_sdk.json
jupyter_sdk-0.0.2.data/data/etc/jupyter/jupyter_server_config.d/jupyter_sdk.json
jupyter_sdk-0.0.2.data/data/share/jupyter/labextensions/@datalayer/jupyter-sdk/build_log.json
jupyter_sdk-0.0.2.data/data/share/jupyter/labextensions/@datalayer/jupyter-sdk/package.json
jupyter_sdk-0.0.2.data/data/share/jupyter/labextensions/@datalayer/jupyter-sdk/schemas/@datalayer/jupyter-sdk/package.json.orig
jupyter_sdk-0.0.2.data/data/share/jupyter/labextensions/@datalayer/jupyter-sdk/schemas/@datalayer/jupyter-sdk/plugin.json
jupyter_sdk-0.0.2.data/data/share/jupyter/labextensions/@datalayer/jupyter-sdk/static/design_icons_lib_index_js.45fbfb5db1770a59a647.js
jupyter_sdk-0.0.2.data/data/share/jupyter/labextensions/@datalayer/jupyter-sdk/static/design_icons_lib_index_js.45fbfb5db1770a59a647.js.map
jupyter_sdk-0.0.2.data/data/share/jupyter/labextensions/@datalayer/jupyter-sdk/static/lib_index_js.27be5e86533ca85ca68e.js
jupyter_sdk-0.0.2.data/data/share/jupyter/labextensions/@datalayer/jupyter-sdk/static/lib_index_js.27be5e86533ca85ca68e.js.map
jupyter_sdk-0.0.2.data/data/share/jupyter/labextensions/@datalayer/jupyter-sdk/static/node_modules_object-assign_index_js.ac1e990cc639a2e98278.js
jupyter_sdk-0.0.2.data/data/share/jupyter/labextensions/@datalayer/jupyter-sdk/static/node_modules_object-assign_index_js.ac1e990cc639a2e98278.js.map
jupyter_sdk-0.0.2.data/data/share/jupyter/labextensions/@datalayer/jupyter-sdk/static/remoteEntry.d74e2d4d8122183b1988.js
jupyter_sdk-0.0.2.data/data/share/jupyter/labextensions/@datalayer/jupyter-sdk/static/remoteEntry.d74e2d4d8122183b1988.js.map
jupyter_sdk-0.0.2.data/data/share/jupyter/labextensions/@datalayer/jupyter-sdk/static/style.js
jupyter_sdk-0.0.2.dist-info/METADATA
jupyter_sdk-0.0.2.dist-info/WHEEL
jupyter_sdk-0.0.2.dist-info/licenses/LICENSE
jupyter_sdk-0.0.2.dist-info/RECORD
